ug_salsa/__init__.py
ug_salsa/analyses/__init__.py
ug_salsa/analyses/analysis.py
ug_salsa/analyses/fwhm_analyses/__init__.py
ug_salsa/analyses/fwhm_analyses/fwhm_analysis.py
ug_salsa/analyses/fwhm_analyses/fwhm_flow1_wafermap.py
ug_salsa/analyses/fwhm_analyses/fwhm_frac_in_spec_wafermap.py
ug_salsa/analyses/fwhm_analyses/fwhm_heatmap.py
ug_salsa/analyses/fwhm_analyses/fwhm_median_wafermap.py
ug_salsa/analyses/fwhm_analyses/fwhm_metrics_table.py
ug_salsa/analyses/fwhm_analyses/fwhm_per_flow.py
ug_salsa/analyses/fwhm_analyses/fwhm_radius_lineplot.py
ug_salsa/analyses/fwhm_analyses/fwhm_std_wafermap.py
ug_salsa/analyses/fwhm_analyses/mean_fwhm_per_flow_by_base.py
ug_salsa/analyses/refbead_analyses/__init__.py
ug_salsa/analyses/refbead_analyses/bead_loss.py
ug_salsa/analyses/refbead_analyses/loading_density_metrics.py
ug_salsa/analyses/refbead_analyses/nsb.py
ug_salsa/analyses/refbead_analyses/optics_qc.py
ug_salsa/analyses/refbead_analyses/plot_anoms_perflow.py
ug_salsa/analyses/refbead_analyses/plot_bead_density.py
ug_salsa/analyses/refbead_analyses/plot_bead_loss_hist1d.py
ug_salsa/analyses/refbead_analyses/plot_bead_loss_hist2d.py
ug_salsa/analyses/refbead_analyses/plot_bead_loss_perflow.py
ug_salsa/analyses/refbead_analyses/plot_bead_loss_wafermap.py
ug_salsa/analyses/refbead_analyses/plot_ref_cv_perflow.py
ug_salsa/analyses/refbead_analyses/plot_ref_firsT.py
ug_salsa/analyses/refbead_analyses/plot_refbead_decay.py
ug_salsa/analyses/refbead_analyses/plot_refbead_density.py
ug_salsa/analyses/refbead_analyses/plot_spacialx_firsT.py
ug_salsa/analyses/refbead_analyses/plot_unstable_tiles.py
ug_salsa/analyses/refbead_analyses/read_TT_heatmap.py
ug_salsa/analyses/refbead_analyses/refbead_analysis.py
ug_salsa/analyses/refbead_analyses/signal_metrics.py
ug_salsa/analyses/refbead_analyses/signal_noise.py
ug_salsa/analyses/refbead_analyses/whole_wafer_average_signal_per_flow.py
ug_salsa/analyses/template_analyses/__init__.py
ug_salsa-0.1.8.dist-info/METADATA
ug_salsa-0.1.8.dist-info/WHEEL
ug_salsa-0.1.8.dist-info/RECORD
