Metadata-Version: 2.1
Name: ug_salsa
Version: 0.1.8
Summary: System Analytics Library for Substrate Analysis
Author: William Huang
Author-email: william.huang@ultimagen.com
Requires-Python: >=3.8,<4.0
Classifier: Programming Language :: Python :: 3
Classifier: Programming Language :: Python :: 3.8
Classifier: Programming Language :: Python :: 3.9
Classifier: Programming Language :: Python :: 3.10
Classifier: Programming Language :: Python :: 3.11
Requires-Dist: boto3
Requires-Dist: fastparquet
Requires-Dist: matplotlib
Requires-Dist: numpy
Requires-Dist: pandas
Requires-Dist: plotly
Requires-Dist: requests
Requires-Dist: scipy
Requires-Dist: tqdm
